fdtdx/__init__.py
fdtdx/config.py
fdtdx/constants.py
fdtdx/materials.py
fdtdx/typing.py
fdtdx/conversion/__init__.py
fdtdx/conversion/export.py
fdtdx/core/__init__.py
fdtdx/core/grid.py
fdtdx/core/linalg.py
fdtdx/core/misc.py
fdtdx/core/switch.py
fdtdx/core/wavelength.py
fdtdx/core/jax/__init__.py
fdtdx/core/jax/pytrees.py
fdtdx/core/jax/sharding.py
fdtdx/core/jax/ste.py
fdtdx/core/jax/utils.py
fdtdx/core/physics/__init__.py
fdtdx/core/physics/curl.py
fdtdx/core/physics/losses.py
fdtdx/core/physics/metrics.py
fdtdx/core/physics/modes.py
fdtdx/core/plotting/__init__.py
fdtdx/core/plotting/colors.py
fdtdx/core/plotting/debug.py
fdtdx/core/plotting/device_permittivity_index_utils.py
fdtdx/core/plotting/utils.py
fdtdx/fdtd/__init__.py
fdtdx/fdtd/backward.py
fdtdx/fdtd/container.py
fdtdx/fdtd/fdtd.py
fdtdx/fdtd/forward.py
fdtdx/fdtd/initialization.py
fdtdx/fdtd/misc.py
fdtdx/fdtd/update.py
fdtdx/fdtd/wrapper.py
fdtdx/interfaces/__init__.py
fdtdx/interfaces/modules.py
fdtdx/interfaces/recorder.py
fdtdx/interfaces/state.py
fdtdx/interfaces/time_filter.py
fdtdx/objects/__init__.py
fdtdx/objects/object.py
fdtdx/objects/boundaries/__init__.py
fdtdx/objects/boundaries/boundary.py
fdtdx/objects/boundaries/initialization.py
fdtdx/objects/boundaries/perfectly_matched_layer.py
fdtdx/objects/boundaries/periodic.py
fdtdx/objects/boundaries/utils.py
fdtdx/objects/detectors/__init__.py
fdtdx/objects/detectors/detector.py
fdtdx/objects/detectors/diffractive.py
fdtdx/objects/detectors/energy.py
fdtdx/objects/detectors/field.py
fdtdx/objects/detectors/mode.py
fdtdx/objects/detectors/phasor.py
fdtdx/objects/detectors/poynting_flux.py
fdtdx/objects/detectors/plotting/__init__.py
fdtdx/objects/detectors/plotting/line_plot.py
fdtdx/objects/detectors/plotting/plot2d.py
fdtdx/objects/detectors/plotting/video.py
fdtdx/objects/device/__init__.py
fdtdx/objects/device/device.py
fdtdx/objects/device/parameters/__init__.py
fdtdx/objects/device/parameters/binary_transform.py
fdtdx-0.4.2.dist-info/METADATA
fdtdx-0.4.2.dist-info/WHEEL
fdtdx-0.4.2.dist-info/licenses/LICENSE
fdtdx-0.4.2.dist-info/RECORD
