Metadata-Version: 2.4
Name: fdtdx
Version: 0.4.2
Summary: A JAX framework for the finite-difference time-domain (FDTD) method for solving Maxwell's equations with a focus on inverse design of photonic devices.
Project-URL: Repository, https://github.com/ymahlau/fdtdx
Project-URL: Documentation, https://ymahlau.github.io/fdtdx/
Author-email: Yannik Mahlau <mahlau@tnt.uni-hannover.de>, Frederik Schubert <schubert@tnt.uni-hannover.de>
License-File: LICENSE
Requires-Python: >=3.11
Requires-Dist: equinox>=0.11.10
Requires-Dist: jax>=0.4.36; platform_system != 'Linux'
Requires-Dist: jax[cuda12]>=0.4.36; platform_system == 'Linux'
Requires-Dist: loguru>=0.7.3
Requires-Dist: matplotlib>=3.9.4
Requires-Dist: moviepy>=2.1.1
Requires-Dist: optax>=0.2.4
Requires-Dist: pytreeclass>=0.11
Requires-Dist: rich>=13.9.4
Requires-Dist: seaborn>=0.13.2
Requires-Dist: tidy3d>=2.8.0
Requires-Dist: trimesh>=4.5.3
